unopy.cpython-39-darwin.so
unopy.dylibs/libstdc++.6.dylib
unopy.dylibs/libgfortran.5.dylib
unopy.dylibs/libquadmath.0.dylib
unopy.dylibs/libgcc_s.1.1.dylib
include/Uno_C_API.h
include/uno.f90
include/uno_int.h
lib/libuno.a
unopy-0.1.2.dist-info/RECORD
unopy-0.1.2.dist-info/WHEEL
unopy-0.1.2.dist-info/METADATA
unopy-0.1.2.dist-info/licenses/LICENSE
