Metadata-Version: 2.4
Name: unopy
Version: 0.1.2
Summary: Uno, a highly customizable SQP & barrier solver for nonlinearly constrained optimization
Author-Email: Charlie Vanaret <vanaret@zib.de>
Maintainer-Email: Charlie Vanaret <vanaret@zib.de>
License-Expression: MIT
Project-URL: Repository, https://github.com/cvanaret/Uno
Project-URL: Issues, https://github.com/cvanaret/Uno/issues
